targetai/__init__.py
targetai/schemas.py
targetai/targetai_token_client.py
targetai/targetai_token_server.py
targetai-0.0.5.dist-info/METADATA
targetai-0.0.5.dist-info/WHEEL
targetai-0.0.5.dist-info/RECORD
