Metadata-Version: 2.4
Name: targetai
Version: 0.0.5
Summary: Python SDK for working with TargetAI tokens
Project-URL: Homepage, https://targetai.ai
Project-URL: Repository, https://github.com/targetai/sdk-python
Project-URL: Documentation, https://docs.targetai.ai/sdk/python
Author-email: TargetAI <support@targetai.ai>
License: MIT
Classifier: Development Status :: 3 - Alpha
Classifier: Intended Audience :: Developers
Classifier: License :: OSI Approved :: MIT License
Classifier: Operating System :: OS Independent
Classifier: Programming Language :: Python :: 3
Classifier: Topic :: Software Development :: Libraries :: Python Modules
Requires-Python: >=3.8
Requires-Dist: aiohttp>=3.8.0
Requires-Dist: fastapi>=0.100.0
Requires-Dist: pydantic>=2.0.0
Requires-Dist: uvicorn[standard]>=0.20.0
